mqt/qubomaker/__init__.py
mqt/qubomaker/graph.py
mqt/qubomaker/py.typed
mqt/qubomaker/qubo_generator.py
mqt/qubomaker/utils.py
mqt/qubomaker/pathfinder/README.md
mqt/qubomaker/pathfinder/__init__.py
mqt/qubomaker/pathfinder/cost_functions.py
mqt/qubomaker/pathfinder/pathfinder.py
mqt/qubomaker/pathfinder/tsplib.py
mqt/qubomaker/pathfinder/resources/constraint.json
mqt/qubomaker/pathfinder/resources/input-format.json
mqt/qubomaker/pathfinder/resources/constraints/path_contains_edges_at_least_once.json
mqt/qubomaker/pathfinder/resources/constraints/path_contains_edges_at_most_once.json
mqt/qubomaker/pathfinder/resources/constraints/path_contains_edges_exactly_once.json
mqt/qubomaker/pathfinder/resources/constraints/path_contains_vertices_at_least_once.json
mqt/qubomaker/pathfinder/resources/constraints/path_contains_vertices_at_most_once.json
mqt/qubomaker/pathfinder/resources/constraints/path_contains_vertices_exactly_once.json
mqt/qubomaker/pathfinder/resources/constraints/path_ends_at.json
mqt/qubomaker/pathfinder/resources/constraints/path_is_valid.json
mqt/qubomaker/pathfinder/resources/constraints/path_maximize_length.json
mqt/qubomaker/pathfinder/resources/constraints/path_minimize_length.json
mqt/qubomaker/pathfinder/resources/constraints/path_position_is.json
mqt/qubomaker/pathfinder/resources/constraints/path_starts_at.json
mqt/qubomaker/pathfinder/resources/constraints/path_vertex_precedence.json
mqt/qubomaker/pathfinder/resources/constraints/paths_share_no_edges.json
mqt/qubomaker/pathfinder/resources/constraints/paths_share_no_vertices.json
mqt.qubomaker-1.0.1.dist-info/LICENSE
mqt.qubomaker-1.0.1.dist-info/METADATA
mqt.qubomaker-1.0.1.dist-info/WHEEL
mqt.qubomaker-1.0.1.dist-info/top_level.txt
mqt.qubomaker-1.0.1.dist-info/RECORD
