Metadata-Version: 2.1
Name: mqt.qubomaker
Version: 1.0.1
Summary: A tool for the automatic generation and combination of QUBO formulations for specific problem classes.
Author-email: Damian Rovara <damian.rovara@tum.de>, Nils Quetschlich <nils.quetschlich@tum.de>, Lukas Burgholzer <lukas.burgholzer@tum.de>
License: MIT License
Project-URL: Homepage, https://github.com/cda-tum/mqt-qubomaker
Project-URL: Documentation, https://mqt.readthedocs.io/projects/qubomaker
Project-URL: Issues, https://github.com/cda-tum/mqt-qubomaker/issues
Project-URL: Discussions, https://github.com/cda-tum/mqt-qubomaker/discussions
Keywords: MQT,quantum-computing,qubo,shortest-path,design-automation
Classifier: Development Status :: 4 - Beta
Classifier: Intended Audience :: Developers
Classifier: License :: OSI Approved :: MIT License
Classifier: Operating System :: Microsoft :: Windows
Classifier: Operating System :: MacOS
Classifier: Operating System :: POSIX :: Linux
Classifier: Programming Language :: Python
Classifier: Programming Language :: Python :: 3
Classifier: Programming Language :: Python :: 3 :: Only
Classifier: Programming Language :: Python :: 3.9
Classifier: Programming Language :: Python :: 3.10
Classifier: Programming Language :: Python :: 3.11
Classifier: Programming Language :: Python :: 3.12
Classifier: Programming Language :: Python :: 3.13
Classifier: Intended Audience :: Science/Research
Classifier: Natural Language :: English
Classifier: Topic :: Scientific/Engineering :: Electronic Design Automation (EDA)
Classifier: Typing :: Typed
Requires-Python: >=3.9
License-File: LICENSE
Requires-Dist: qiskit >=1.0.0
Requires-Dist: joblib >=1.3.2
Requires-Dist: numpy >=1.22
Requires-Dist: sympy >=1.13.1
Requires-Dist: networkx >=2.8.8
Requires-Dist: docplex >=2.25.236
Requires-Dist: qiskit-optimization >=0.6.0
Requires-Dist: tsplib95 >=0.7.1
Requires-Dist: jsonschema >=4.20.0
Requires-Dist: IPython >=8.12.1
Requires-Dist: ipywidgets >=8.1.1
Requires-Dist: typing-extensions >=4.8.0
Requires-Dist: importlib-resources >=5.0 ; python_version < "3.10"
Requires-Dist: matplotlib >=3.7.0 ; python_version <= "3.11"
Requires-Dist: matplotlib >=3.9.0 ; python_version > "3.11"
Requires-Dist: numpy >=1.24 ; python_version >= "3.11"
Requires-Dist: numpy >=1.26 ; python_version >= "3.12"
Provides-Extra: coverage
Requires-Dist: mqt.qubomaker[test] ; extra == 'coverage'
Requires-Dist: pytest-cov >=4 ; extra == 'coverage'
Provides-Extra: dev
Requires-Dist: mqt.qubomaker[coverage,docs] ; extra == 'dev'
Provides-Extra: docs
Requires-Dist: furo >=2023.9.10 ; extra == 'docs'
Requires-Dist: setuptools-scm >=8.1 ; extra == 'docs'
Requires-Dist: sphinxcontrib-bibtex >=2.4.2 ; extra == 'docs'
Requires-Dist: sphinx-copybutton >=0.5 ; extra == 'docs'
Requires-Dist: ipykernel ; extra == 'docs'
Requires-Dist: nbsphinx ; extra == 'docs'
Requires-Dist: sphinxext-opengraph >=0.9 ; extra == 'docs'
Requires-Dist: sphinx-autodoc-typehints ; extra == 'docs'
Requires-Dist: qiskit[visualization] ; extra == 'docs'
Provides-Extra: test
Requires-Dist: pytest >=7.2 ; extra == 'test'
